README.txt
setup.cfg
setup.py
rfxengine/__init__.py
rfxengine/abac.py
rfxengine/config.py
rfxengine/exceptions.py
rfxengine/memstate.py
rfxengine.egg-info/PKG-INFO
rfxengine.egg-info/SOURCES.txt
rfxengine.egg-info/dependency_links.txt
rfxengine.egg-info/entry_points.txt
rfxengine.egg-info/requires.txt
rfxengine.egg-info/top_level.txt
rfxengine/db/__init__.py
rfxengine/db/get_mysql_connector.py
rfxengine/db/mxsql.py
rfxengine/db/objects.py
rfxengine/db/pool.py
rfxengine/server/__init__.py
rfxengine/server/cherry.py
rfxengine/server/endpoints.py