Metadata-Version: 1.0
Name: rfxengine
Version: 1807.8.6
Summary: Reflex - Container Config and Secret Management - engine
Home-page: https://reflex.cold.org/
Author: Brandon Gillespie
Author-email: bjg-pypi@cold.org
License: UNKNOWN
Keywords: docker,config,secrets
Platform: UNKNOWN
